[{"Names":"orange","Integer Variable":8,"Decimal Variable":3.5},{"Names":"apple","Integer Variable":5,"Decimal Variable":0.89},{"Names":"orange","Integer Variable":4,"Decimal Variable":0.76},{"Names":"orange","Integer Variable":8,"Decimal Variable":0.77},{"Names":"apple","Integer Variable":8,"Decimal Variable":1.28},{"Names":"apple","Integer Variable":3,"Decimal Variable":2.2},{"Names":"orange","Integer Variable":6,"Decimal Variable":1.81},{"Names":"banana","Integer Variable":5,"Decimal Variable":1.22},{"Names":"orange","Integer Variable":2,"Decimal Variable":2.57},{"Names":"orange","Integer Variable":8,"Decimal Variable":0.59}]